{
    "id": "capkcks-fvtt-stuff",
    "title": "cAPKck's FVTT stuff",
    "version": "1.0.0",
    "description": "A collection of various tweaks and functions for Foundry VTT.",
    "compatibility": {
        "minimum": "13",
        "verified": "13.351"
    },
    "esmodules": ["scripts/core.mjs"],
    "styles": [],
    "relationships": {
        "systems": [
            {
                "id": "dnd5e",
                "type": "system",
                "compatibility": {
                    "minimum": "5.2.5",
                    "verified": "5.2.5"
                }
            }
        ]
    },
    "languages": [
        {
            "lang": "en",
            "name": "English",
            "path": "lang/en.json"
        }
    ],
    "authors": [
        {
            "name": "cAPKck",
            "email": "cAPKck@profil6.com",
            "discord": "capkck"
        }
    ],
    "url": "https://github.com/cAPKck/capkcks-fvtt-stuff",
    "manifest": "https://github.com/cAPKck/capkcks-fvtt-stuff/releases/latest/download/module.json",
    "download": "https://github.com/cAPKck/capkcks-fvtt-stuff/releases/download/release-0.3.0/module.zip",
    "license": "LICENSE",
    "readme": "README.md",
    "bugs": "https://github.com/cAPKck/capkcks-fvtt-stuff/issues",
    "changelog": "https://github.com/cAPKck/capkcks-fvtt-stuff/releases",
    "library": false
}
